cloudflare_ai_python/__init__.py
cloudflare_ai_python-0.1.0.dist-info/licenses/LICENSE
tests/__init__.py
tests/test_cloudflare_ai.py
tests/test_cloudflare_ai_python.py
cloudflare_ai_python-0.1.0.dist-info/METADATA
cloudflare_ai_python-0.1.0.dist-info/WHEEL
cloudflare_ai_python-0.1.0.dist-info/top_level.txt
cloudflare_ai_python-0.1.0.dist-info/RECORD
