Metadata-Version: 2.4
Name: cloudflare-ai-python
Version: 0.1.0
Summary: A Python client for Cloudflare Workers AI
Home-page: https://github.com/him6794/cloudflare-ai
Author: Your Name
Author-email: him6794 <justin@justin0711.com>
Classifier: Programming Language :: Python :: 3
Classifier: License :: OSI Approved :: MIT License
Classifier: Operating System :: OS Independent
Requires-Python: >=3.6
License-File: LICENSE
Requires-Dist: requests
Provides-Extra: dev
Requires-Dist: pytest; extra == "dev"
Requires-Dist: flake8; extra == "dev"
Dynamic: author
Dynamic: home-page
Dynamic: license-file
Dynamic: requires-python
